AUTHORS
MANIFEST.in
README
run_game.py
setup.py
korovic/__init__.py
korovic/__main__.py
korovic/background.py
korovic/camera.py
korovic/constants.py
korovic/controllers.py
korovic/cutscene.py
korovic/editor.py
korovic/editor_hud.py
korovic/game.py
korovic/hud.py
korovic/loader.py
korovic/primitives.py
korovic/scene.py
korovic/screenshot.py
korovic/sound.py
korovic/vector.py
korovic/world.py
korovic.egg-info/PKG-INFO
korovic.egg-info/SOURCES.txt
korovic.egg-info/dependency_links.txt
korovic.egg-info/entry_points.txt
korovic.egg-info/requires.txt
korovic.egg-info/top_level.txt
korovic/components/__init__.py
korovic/components/balloons.py
korovic/components/base.py
korovic/components/engines.py
korovic/components/fuel.py
korovic/components/obstacles.py
korovic/components/squid.py
korovic/components/wings.py
korovic/data/components/aerolon.json
korovic/data/components/balloon.json
korovic/data/components/barrageballoon.json
korovic/data/components/biplanewing.json
korovic/data/components/ekranoplan.json
korovic/data/components/hangglider.json
korovic/data/components/hotairballoon.json
korovic/data/components/jetengine.json
korovic/data/components/largefueltank.json
korovic/data/components/propeller.json
korovic/data/components/pulsejet.json
korovic/data/components/rocket.json
korovic/data/components/rotor.json
korovic/data/components/smallfueltank.json
korovic/data/components/susie.json
korovic/data/components/tentaclespike.json
korovic/data/components/thruster.json
korovic/data/components/wing.json
korovic/data/cutscene/aerial.png
korovic/data/cutscene/beach.png
korovic/data/cutscene/blup.png
korovic/data/cutscene/bubble-tail.png
korovic/data/cutscene/exclamation.png
korovic/data/cutscene/korovic-elated.png
korovic/data/cutscene/korovic-pointing.png
korovic/data/cutscene/korovic-standing.png
korovic/data/cutscene/squee.png
korovic/data/cutscene/susie-dipping.png
korovic/data/cutscene/susie-puffing1.png
korovic/data/cutscene/susie-puffing2.png
korovic/data/cutscene/susie-standing.png
korovic/data/fonts/atomic-clock-radio.ttf
korovic/data/levels/freeflight.svg
korovic/data/levels/level1.svg
korovic/data/levels/level2.svg
korovic/data/levels/level3.svg
