Metadata-Version: 1.0
Name: korovic
Version: 1.1.0
Summary: Dr. Korovic's Flying Atomic Squid
Home-page: http://www.pyweek.org/e/wasabi/
Author: Daniel Pope
Author-email: lord.mauve@gmail.com
License: UNKNOWN
Platform: UNKNOWN
